rtl/display_system.v
`timescale 1ns / 1ps

module display_system (
    input wire clk,             // Clock signal
    input wire reset,           // Reset signal
    input wire [23:0] pixel_data, // 24-bit pixel data (8 bits for R, G, B)
    output reg [7:0] r,         // Red component
    output reg [7:0] g,         // Green component
    output reg [7:0] b,         // Blue component
    output reg hsync,           // Horizontal sync
    output reg vsync            // Vertical sync
);

    // Horizontal and vertical counters
    reg [10:0] h_count;
    reg [9:0] v_count;

    // Parameters for display timing (for a 640x480 resolution as an example)
    localparam H_TOTAL = 800;
    localparam H_DISPLAY = 640;
    localparam H_FRONT_PORCH = 16;
    localparam H_SYNC_PULSE = 96;

    localparam V_TOTAL = 525;
    localparam V_DISPLAY = 480;
    localparam V_FRONT_PORCH = 10;
    localparam V_SYNC_PULSE = 2;

    // Horizontal and vertical sync signals
    always @(posedge clk or posedge reset) begin
        if (reset) begin
            h_count <= 0;
            v_count <= 0;
            hsync <= 1;
            vsync <= 1;
        end else begin
            // Horizontal counter
            if (h_count < H_TOTAL - 1) begin
                h_count <= h_count + 1;
            end else begin
                h_count <= 0;
                // Vertical counter
                if (v_count < V_TOTAL - 1) begin
                    v_count <= v_count + 1;
                end else begin
                    v_count <= 0;
                end
            end

            // Horizontal sync signal generation
            if (h_count < H_SYNC_PULSE) begin
                hsync <= 0;
            end else begin
                hsync <= 1;
            end

            // Vertical sync signal generation
            if (v_count < V_SYNC_PULSE) begin
                vsync <= 0;
            end else begin
                vsync <= 1;
            end

            // Display pixel data when within display area
            if (h_count < H_DISPLAY && v_count < V_DISPLAY) begin
                r <= pixel_data[23:16]; // Red component
                g <= pixel_data[15:8];  // Green component
                b <= pixel_data[7:0];   // Blue component
            end else begin
                r <= 0;
                g <= 0;
                b <= 0;
            end
        end
    end

endmodule

rtl/display_system_tb.v
`timescale 1ns / 1ps

module display_system_tb;

    // Testbench signals
    reg clk;
    reg reset;
    reg [23:0] pixel_data;
    wire [7:0] r;
    wire [7:0] g;
    wire [7:0] b;
    wire hsync;
    wire vsync;

    // Instantiate the display system module
    display_system uut (
        .clk(clk),
        .reset(reset),
        .pixel_data(pixel_data),
        .r(r),
        .g(g),
        .b(b),
        .hsync(hsync),
        .vsync(vsync)
    );

    // Clock generation
    initial begin
        clk = 0;
        forever #5 clk = ~clk; // 100 MHz clock (10 ns period)
    end
    
    initial begin
        // Open VCD file for waveform dump
        $dumpfile("display_system_waveform.vcd");
        $dumpvars(0, display_system_tb);
    end

    // Test sequence
    initial begin
        // Initialize signals
        reset = 1;
        pixel_data = 24'h000000;
        #20;

        // Release reset
        reset = 0;
        #20;

        // Apply some pixel data
        pixel_data = 24'hFF0000; // Red pixel
        #100;
        pixel_data = 24'h00FF00; // Green pixel
        #100;
        pixel_data = 24'h0000FF; // Blue pixel
        #100;

        // Simulate reset condition
        reset = 1;
        #20;
        reset = 0;
        #100;

        // End simulation
        $finish;
    end

    // Monitor outputs
    initial begin
        $monitor("Time=%0d | R=%h, G=%h, B=%h, HSYNC=%b, VSYNC=%b", $time, r, g, b, hsync, vsync);
    end

endmodule

rtl/display_system_waveform.vcd
$date
	Tue Nov 12 16:18:35 2024
$end
$version
	Icarus Verilog
$end
$timescale
	1ps
$end
$scope module display_system_tb $end
$var wire 1 ! vsync $end
$var wire 8 " r [7:0] $end
$var wire 1 # hsync $end
$var wire 8 $ g [7:0] $end
$var wire 8 % b [7:0] $end
$var reg 1 & clk $end
$var reg 24 ' pixel_data [23:0] $end
$var reg 1 ( reset $end
$scope module uut $end
$var wire 1 & clk $end
$var wire 24 ) pixel_data [23:0] $end
$var wire 1 ( reset $end
$var parameter 32 * H_DISPLAY $end
$var parameter 32 + H_FRONT_PORCH $end
$var parameter 32 , H_SYNC_PULSE $end
$var parameter 32 - H_TOTAL $end
$var parameter 32 . V_DISPLAY $end
$var parameter 32 / V_FRONT_PORCH $end
$var parameter 32 0 V_SYNC_PULSE $end
$var parameter 32 1 V_TOTAL $end
$var reg 8 2 b [7:0] $end
$var reg 8 3 g [7:0] $end
$var reg 11 4 h_count [10:0] $end
$var reg 1 # hsync $end
$var reg 8 5 r [7:0] $end
$var reg 10 6 v_count [9:0] $end
$var reg 1 ! vsync $end
$upscope $end
$upscope $end
$enddefinitions $end
$comment Show the parameter values. $end
$dumpall
b1000001101 1
b10 0
b1010 /
b111100000 .
b1100100000 -
b1100000 ,
b10000 +
b1010000000 *
$end
#0
$dumpvars
b0 6
bx 5
b0 4
bx 3
bx 2
b0 )
1(
b0 '
0&
bx %
bx $
1#
bx "
1!
$end
#5000
1&
#10000
0&
#15000
1&
#20000
0&
0(
#25000
b0 %
b0 2
b0 $
b0 3
b0 "
b0 5
0!
0#
b1 4
1&
#30000
0&
#35000
b10 4
1&
#40000
0&
b111111110000000000000000 '
b111111110000000000000000 )
#45000
b11111111 "
b11111111 5
b11 4
1&
#50000
0&
#55000
b100 4
1&
#60000
0&
#65000
b101 4
1&
#70000
0&
#75000
b110 4
1&
#80000
0&
#85000
b111 4
1&
#90000
0&
#95000
b1000 4
1&
#100000
0&
#105000
b1001 4
1&
#110000
0&
#115000
b1010 4
1&
#120000
0&
#125000
b1011 4
1&
#130000
0&
#135000
b1100 4
1&
#140000
0&
b1111111100000000 '
b1111111100000000 )
#145000
b11111111 $
b11111111 3
b0 "
b0 5
b1101 4
1&
#150000
0&
#155000
b1110 4
1&
#160000
0&
#165000
b1111 4
1&
#170000
0&
#175000
b10000 4
1&
#180000
0&
#185000
b10001 4
1&
#190000
0&
#195000
b10010 4
1&
#200000
0&
#205000
b10011 4
1&
#210000
0&
#215000
b10100 4
1&
#220000
0&
#225000
b10101 4
1&
#230000
0&
#235000
b10110 4
1&
#240000
0&
b11111111 '
b11111111 )
#245000
b11111111 %
b11111111 2
b0 $
b0 3
b10111 4
1&
#250000
0&
#255000
b11000 4
1&
#260000
0&
#265000
b11001 4
1&
#270000
0&
#275000
b11010 4
1&
#280000
0&
#285000
b11011 4
1&
#290000
0&
#295000
b11100 4
1&
#300000
0&
#305000
b11101 4
1&
#310000
0&
#315000
b11110 4
1&
#320000
0&
#325000
b11111 4
1&
#330000
0&
#335000
b100000 4
1&
#340000
1!
1#
b0 4
0&
1(
#345000
1&
#350000
0&
#355000
1&
#360000
0&
0(
#365000
0!
0#
b1 4
1&
#370000
0&
#375000
b10 4
1&
#380000
0&
#385000
b11 4
1&
#390000
0&
#395000
b100 4
1&
#400000
0&
#405000
b101 4
1&
#410000
0&
#415000
b110 4
1&
#420000
0&
#425000
b111 4
1&
#430000
0&
#435000
b1000 4
1&
#440000
0&
#445000
b1001 4
1&
#450000
0&
#455000
b1010 4
1&
