rtl/apix_transmitter.v
module apix_transmitter (
    input wire        clk,         // Clock signal
    input wire        rst_n,       // Active-low reset
    input wire [23:0] pixel_data,  // 24-bit pixel data (RGB)
    input wire        pixel_valid, // Pixel data valid signal
    output reg        apix_data,   // Serialized data output
    output wire       apix_clk     // Transmit clock output
);

    // Internal signals
    reg [31:0] frame_counter;       // Frame counter for video frames
    reg [15:0] line_counter;        // Line counter for 1080 lines/frame
    reg [7:0]  crc;                 // CRC for error detection
    reg [23:0] pixel_buffer;        // Pixel data buffer
    reg [7:0]  serdes_data;         // Serialized 8-bit data
    reg [2:0]  serdes_counter;      // Counter for 8-bit SerDes cycles
    reg        data_ready;          // Data ready for transmission

    // State machine states
    localparam IDLE = 2'b00, SYNC = 2'b01, DATA = 2'b10, CRC = 2'b11;
    reg [1:0]  state, next_state;

    // Clock output assignment
    assign apix_clk = clk;

    // Main sequential process
    always @(posedge clk or negedge rst_n) begin
        if (!rst_n) begin
            // Reset all signals
            state <= IDLE;
            frame_counter <= 0;
            line_counter <= 0;
            crc <= 8'h00;
            serdes_counter <= 0;
            data_ready <= 0;
        end else begin
            state <= next_state;
            
            // Frame and line counting logic
            if (state == SYNC) begin
                frame_counter <= frame_counter + 1;
                line_counter <= 0;
            end else if (state == DATA && pixel_valid) begin
                line_counter <= line_counter + 1;
            end

            // CRC calculation (XOR over pixel data)
            if (state == DATA && pixel_valid) begin
                crc <= crc ^ pixel_data[7:0] ^ pixel_data[15:8] ^ pixel_data[23:16];
                pixel_buffer <= pixel_data;
            end

            // SerDes serialization logic
            if (serdes_counter == 3'b111) begin
                serdes_counter <= 0;
                data_ready <= 1; // Data is ready to transmit
            end else begin
                serdes_counter <= serdes_counter + 1;
                data_ready <= 0;
            end
        end
    end

    // Next state logic (state machine)
    always @(*) begin
        case (state)
            IDLE: next_state = (pixel_valid) ? SYNC : IDLE;
            SYNC: next_state = DATA;
            DATA: next_state = (line_counter == 1079) ? CRC : DATA; // After 1080 lines, move to CRC
            CRC:  next_state = IDLE; // After CRC, return to IDLE
            default: next_state = IDLE;
        endcase
    end

    // Serialization of pixel data and CRC
    always @(*) begin
        case (state)
            SYNC: serdes_data = 8'hFF; // Sync pattern
            DATA: begin
                case (serdes_counter)
                    3'b000: serdes_data = pixel_buffer[23:16]; // Red
                    3'b001: serdes_data = pixel_buffer[15:8];  // Green
                    3'b010: serdes_data = pixel_buffer[7:0];   // Blue
                    default: serdes_data = 8'h00; // Default when no data
                endcase
            end
            CRC:  serdes_data = crc; // CRC transmission
            default: serdes_data = 8'h00;
        endcase
    end

    // Output serialized data
    always @(posedge clk or negedge rst_n) begin
        if (!rst_n) begin
            apix_data <= 0;
        end else if (data_ready) begin
            apix_data <= serdes_data[serdes_counter]; // Transmit serial data bit by bit
        end
    end

endmodule

rtl/testbench/apix_transmitter_tb.v
`timescale 1ns/1ps

module apix_transmitter_tb;

    // Test bench signals
    reg clk;
    reg rst_n;
    reg [23:0] pixel_data;
    reg pixel_valid;
    wire apix_data;
    wire apix_clk;

    // Clock generation parameters
    parameter CLK_PERIOD = 10; // 100MHz clock

    // Instantiate the APIX transmitter
    apix_transmitter dut (
        .clk(clk),
        .rst_n(rst_n),
        .pixel_data(pixel_data),
        .pixel_valid(pixel_valid),
        .apix_data(apix_data),
        .apix_clk(apix_clk)
    );

    // Clock generation
    initial begin
        clk = 0;
        forever #(CLK_PERIOD/2) clk = ~clk;
    end

    // Test stimulus
    initial begin
        // Initialize signals
        rst_n = 0;
        pixel_data = 24'h000000;
        pixel_valid = 0;

        // Initialize dump file
        $dumpfile("apix_transmitter_tb.vcd");
        $dumpvars(0, apix_transmitter_tb);

        // Reset sequence
        #(CLK_PERIOD*5);
        rst_n = 1;
        #(CLK_PERIOD*5);

        // Test Case 1: Single pixel transmission
        pixel_data = 24'hAB_CD_EF;
        pixel_valid = 1;
        #(CLK_PERIOD*10);
        pixel_valid = 0;
        #(CLK_PERIOD*10);

        // Test Case 2: Multiple pixel transmission
        repeat(5) begin
            pixel_data = $random;  // Generate random pixel data
            pixel_valid = 1;
            #(CLK_PERIOD*8);  // Wait for 8 clock cycles per pixel
        end
        pixel_valid = 0;
        #(CLK_PERIOD*10);

        // Test Case 3: Line transmission (simplified)
        pixel_valid = 1;
        repeat(1080) begin  // Simulate one line of 1080p
            pixel_data = $random;
            #(CLK_PERIOD*8);
        end
        pixel_valid = 0;
        #(CLK_PERIOD*20);

        // Test Case 4: Reset during transmission
        pixel_data = 24'h55_AA_55;
        pixel_valid = 1;
        #(CLK_PERIOD*5);
        rst_n = 0;  // Assert reset
        #(CLK_PERIOD*5);
        rst_n = 1;  // De-assert reset
        #(CLK_PERIOD*10);
        pixel_valid = 0;

        // Add delay before ending simulation
        #(CLK_PERIOD*50);
        
        // End simulation
        $display("Simulation completed successfully");
        $finish;
    end

    // Monitor changes
    always @(posedge clk) begin
        if (pixel_valid)
            $display("Time=%0t pixel_data=%h apix_data=%b", $time, pixel_data, apix_data);
    end

    // Assertions
    // initial begin
    //     // Check reset behavior
    //     assert property (@(posedge clk) !rst_n |-> apix_data == 1'b0)
    //     else $error("Reset assertion failed");

    //     // Check that apix_clk matches input clock
    //     assert property (@(posedge clk) apix_clk == clk)
    //     else $error("Clock assertion failed");
    // end

    // Reset behavior check (Manual check instead of assertion)
    always @(posedge clk) begin
        if (!rst_n && apix_data !== 1'b0) begin
            $error("Reset behavior failed: apix_data should be 0 during reset");
        end
    end

    // Clock check (Manual check instead of assertion)
    always @(posedge clk) begin
        if (apix_clk !== clk) begin
            $error("Clock behavior failed: apix_clk does not match input clock");
        end
    end

    // Optional: CRC verification
    reg [7:0] expected_crc;
    always @(posedge clk) begin
        if (dut.state == dut.CRC) begin
            $display("Time=%0t CRC=%h", $time, dut.crc);
        end
    end

endmodule

rtl/sim_files/apix_transmitter_tb.vcd
$date
	Tue Nov 12 15:02:54 2024
$end
$version
	Icarus Verilog
$end
$timescale
	1ps
$end
$scope module apix_transmitter_tb $end
$var wire 1 ! apix_data $end
$var wire 1 " apix_clk $end
$var parameter 32 # CLK_PERIOD $end
$var reg 1 $ clk $end
$var reg 24 % pixel_data [23:0] $end
$var reg 1 & pixel_valid $end
$var reg 1 ' rst_n $end
$scope module dut $end
$var wire 1 " apix_clk $end
$var wire 1 $ clk $end
$var wire 24 ( pixel_data [23:0] $end
$var wire 1 & pixel_valid $end
$var wire 1 ' rst_n $end
$var parameter 2 ) CRC $end
$var parameter 2 * DATA $end
$var parameter 2 + IDLE $end
$var parameter 2 , SYNC $end
$var reg 1 ! apix_data $end
$var reg 8 - crc [7:0] $end
$var reg 1 . data_ready $end
$var reg 32 / frame_counter [31:0] $end
$var reg 16 0 line_counter [15:0] $end
$var reg 2 1 next_state [1:0] $end
$var reg 24 2 pixel_buffer [23:0] $end
$var reg 3 3 serdes_counter [2:0] $end
$var reg 8 4 serdes_data [7:0] $end
$var reg 2 5 state [1:0] $end
$upscope $end
$upscope $end
$enddefinitions $end
$comment Show the parameter values. $end
$dumpall
b1 ,
b0 +
b10 *
b11 )
b1010 #
$end
#0
$dumpvars
b0 5
b0 4
b0 3
bx 2
b0 1
b0 0
b0 /
0.
b0 -
b0 (
0'
0&
b0 %
0$
0"
0!
$end
#5000
1"
1$
#10000
0"
0$
#15000
1"
1$
#20000
0"
0$
#25000
1"
1$
#30000
0"
0$
#35000
1"
1$
#40000
0"
0$
#45000
1"
1$
#50000
0"
0$
1'
#55000
b1 3
1"
1$
#60000
0"
0$
#65000
b10 3
1"
1$
#70000
0"
0$
#75000
b11 3
1"
1$
#80000
0"
0$
#85000
b100 3
1"
1$
#90000
0"
0$
#95000
b101 3
1"
1$
#100000
b1 1
0"
0$
1&
b101010111100110111101111 %
b101010111100110111101111 (
#105000
b11111111 4
b10 1
b110 3
b1 5
1"
1$
#110000
0"
0$
#115000
b0 4
b111 3
b1 /
b10 5
1"
1$
#120000
0"
0$
#125000
b10101011 4
1.
b0 3
b101010111100110111101111 2
b10001001 -
b1 0
1"
1$
#130000
0"
0$
#135000
b11001101 4
0.
b1 3
b0 -
b10 0
1!
1"
1$
#140000
0"
0$
#145000
b11101111 4
b10 3
b10001001 -
b11 0
1"
1$
#150000
0"
0$
#155000
b0 4
b11 3
b0 -
b100 0
1"
1$
#160000
0"
0$
#165000
b100 3
b10001001 -
b101 0
1"
1$
#170000
0"
0$
#175000
b101 3
b0 -
b110 0
1"
1$
#180000
0"
0$
#185000
b110 3
b10001001 -
b111 0
1"
1$
#190000
0"
0$
#195000
b111 3
b0 -
b1000 0
1"
1$
#200000
0"
0$
0&
#205000
b10101011 4
1.
b0 3
1"
1$
#210000
0"
0$
#215000
b11001101 4
0.
b1 3
1"
1$
#220000
0"
0$
#225000
b11101111 4
b10 3
1"
1$
#230000
0"
0$
#235000
b0 4
b11 3
1"
1$
#240000
0"
0$
#245000
b100 3
1"
1$
#250000
0"
0$
#255000
b101 3
1"
1$
#260000
0"
0$
#265000
b110 3
1"
1$
#270000
0"
0$
#275000
b111 3
1"
1$
#280000
0"
0$
#285000
b10101011 4
1.
b0 3
1"
1$
#290000
0"
0$
#295000
b11001101 4
0.
b1 3
1"
1$
#300000
0"
0$
1&
b101010011010100100100 %
b101010011010100100100 (
#305000
b100100 4
b10 3
b101010011010100100100 2
b100 -
b1001 0
1"
1$
#310000
0"
0$
#315000
b0 4
b11 3
b0 -
b1010 0
1"
1$
#320000
0"
0$
#325000
b100 3
b100 -
b1011 0
1"
1$
#330000
0"
0$
#335000
b101 3
b0 -
b1100 0
1"
1$
#340000
0"
0$
#345000
b110 3
b100 -
b1101 0
1"
1$
#350000
0"
0$
#355000
b111 3
b0 -
b1110 0
1"
1$
#360000
0"
0$
#365000
b10101 4
1.
b0 3
b100 -
b1111 0
1"
1$
#370000
0"
0$
#375000
b110101 4
0.
b1 3
b0 -
b10000 0
1"
1$
#380000
0"
0$
b100010010101111010000001 %
b100010010101111010000001 (
#385000
b10000001 4
b10 3
b100010010101111010000001 2
b1010110 -
b10001 0
1"
1$
#390000
0"
0$
#395000
b0 4
b11 3
b0 -
b10010 0
1"
1$
#400000
0"
0$
#405000
b100 3
b1010110 -
b10011 0
1"
1$
#410000
0"
0$
#415000
b101 3
b0 -
b10100 0
1"
1$
#420000
0"
0$
#425000
b110 3
b1010110 -
b10101 0
1"
1$
#430000
0"
0$
#435000
b111 3
b0 -
b10110 0
1"
1$
#440000
0"
0$
#445000
b10001001 4
1.
b0 3
b1010110 -
b10111 0
1"
1$
#450000
0"
0$
#455000
b1011110 4
0.
b1 3
b0 -
b11000 0
1"
1$
#460000
0"
0$
b100001001101011000001001 %
b100001001101011000001001 (
#465000
b1001 4
b10 3
b100001001101011000001001 2
b1011011 -
b11001 0
1"
1$
#470000
0"
0$
#475000
b0 4
b11 3
b0 -
b11010 0
1"
1$
#480000
0"
0$
#485000
b100 3
b1011011 -
b11011 0
1"
1$
#490000
0"
0$
#495000
b101 3
b0 -
b11100 0
1"
1$
#500000
0"
0$
#505000
b110 3
b1011011 -
b11101 0
1"
1$
#510000
0"
0$
#515000
b111 3
b0 -
b11110 0
1"
1$
#520000
0"
0$
#525000
b10000100 4
1.
b0 3
b1011011 -
b11111 0
1"
1$
#530000
0"
0$
#535000
b11010110 4
0.
b1 3
b0 -
b100000 0
0!
1"
1$
#540000
0"
0$
b111100000101011001100011 %
b111100000101011001100011 (
#545000
b1100011 4
b10 3
b111100000101011001100011 2
b11000101 -
b100001 0
1"
1$
#550000
0"
0$
#555000
b0 4
b11 3
b0 -
b100010 0
1"
1$
#560000
0"
0$
#565000
b100 3
b11000101 -
b100011 0
1"
1$
#570000
0"
0$
#575000
b101 3
b0 -
b100100 0
1"
1$
#580000
0"
0$
#585000
b110 3
b11000101 -
b100101 0
1"
1$
#590000
0"
0$
#595000
b111 3
b0 -
b100110 0
1"
1$
#600000
0"
0$
#605000
b11110000 4
1.
b0 3
b11000101 -
b100111 0
1"
1$
#610000
0"
0$
#615000
b1010110 4
0.
b1 3
b0 -
b101000 0
1"
1$
#620000
0"
0$
b101110010111101100001101 %
b101110010111101100001101 (
#625000
b1101 4
b10 3
b101110010111101100001101 2
b11001111 -
b101001 0
1"
1$
#630000
0"
0$
#635000
b0 4
b11 3
b0 -
b101010 0
1"
1$
#640000
0"
0$
#645000
b100 3
b11001111 -
b101011 0
1"
1$
#650000
0"
0$
#655000
b101 3
b0 -
b101100 0
1"
1$
#660000
0"
0$
#665000
b110 3
b11001111 -
b101101 0
1"
1$
#670000
0"
0$
#675000
b111 3
b0 -
b101110 0
1"
1$
#680000
0"
0$
#685000
b10111001 4
1.
b0 3
b11001111 -
b101111 0
1"
1$
#690000
0"
0$
#695000
b1111011 4
0.
b1 3
b0 -
b110000 0
1!
1"
1$
#700000
0"
0$
0&
#705000
b1101 4
b10 3
1"
1$
#710000
0"
0$
#715000
b0 4
b11 3
1"
1$
#720000
0"
0$
#725000
b100 3
1"
1$
#730000
0"
0$
#735000
b101 3
1"
1$
#740000
0"
0$
#745000
b110 3
1"
1$
#750000
0"
0$
#755000
b111 3
1"
1$
#760000
0"
0$
#765000
b10111001 4
1.
b0 3
1"
1$
#770000
0"
0$
#775000
b1111011 4
0.
b1 3
1"
1$
#780000
0"
0$
#785000
b1101 4
b10 3
1"
1$
#790000
0"
0$
#795000
b0 4
b11 3
1"
1$
#800000
0"
0$
b110111111001100110001101 %
b110111111001100110001101 (
1&
#805000
b100 3
b110111111001100110001101 2
b11001011 -
b110001 0
1"
1$
#810000
0"
0$
#815000
b101 3
b0 -
b110010 0
1"
1$
#820000
0"
0$
#825000
b110 3
b11001011 -
b110011 0
1"
1$
#830000
0"
0$
#835000
b111 3
b0 -
b110100 0
1"
1$
#840000
0"
0$
#845000
b11011111 4
1.
b0 3
b11001011 -
b110101 0
1"
1$
#850000
0"
0$
#855000
b10011001 4
0.
b1 3
b0 -
b110110 0
1"
1$
#860000
0"
0$
#865000
b10001101 4
b10 3
b11001011 -
b110111 0
1"
1$
#870000
0"
0$
#875000
b0 4
b11 3
b0 -
b111000 0
1"
1$
#880000
0"
0$
b110000101000010001100101 %
b110000101000010001100101 (
#885000
b100 3
b110000101000010001100101 2
b100011 -
b111001 0
1"
1$
#890000
0"
0$
#895000
b101 3
b0 -
b111010 0
1"
1$
#900000
0"
0$
#905000
b110 3
b100011 -
b111011 0
1"
1$
#910000
0"
0$
#915000
b111 3
b0 -
b111100 0
1"
1$
#920000
0"
0$
#925000
b11000010 4
1.
b0 3
b100011 -
b111101 0
1"
1$
#930000
0"
0$
#935000
b10000100 4
0.
b1 3
b0 -
b111110 0
0!
1"
1$
#940000
0"
0$
#945000
b1100101 4
b10 3
b100011 -
b111111 0
1"
1$
#950000
0"
0$
#955000
b0 4
b11 3
b0 -
b1000000 0
1"
1$
#960000
0"
0$
b1101110101001000010010 %
b1101110101001000010010 (
#965000
b100 3
b1101110101001000010010 2
b1110111 -
b1000001 0
1"
1$
#970000
0"
0$
#975000
b101 3
b0 -
b1000010 0
1"
1$
#980000
0"
0$
#985000
b110 3
b1110111 -
b1000011 0
1"
1$
#990000
0"
0$
#995000
b111 3
b0 -
b1000100 0
1"
1$
#1000000
0"
0$
#1005000
b110111 4
1.
b0 3
b1110111 -
b1000101 0
1"
1$
#1010000
0"
0$
#1015000
b1010010 4
0.
b1 3
b0 -
b1000110 0
1!
1"
1$
#1020000
0"
0$
#1025000
b10010 4
b10 3
b1110111 -
b1000111 0
1"
1$
#1030000
0"
0$
#1035000
b0 4
b11 3
b0 -
b1001000 0
1"
1$
#1040000
0"
0$
b111100111110001100000001 %
b111100111110001100000001 (
#1045000
b100 3
b111100111110001100000001 2
b10001 -
b1001001 0
1"
1$
#1050000
0"
0$
#1055000
b101 3
b0 -
b1001010 0
1"
1$
#1060000
0"
0$
#1065000
b110 3
b10001 -
b1001011 0
1"
1$
#1070000
0"
0$
#1075000
b111 3
b0 -
b1001100 0
1"
1$
#1080000
0"
0$
#1085000
b11110011 4
1.
b0 3
b10001 -
b1001101 0
1"
1$
#1090000
0"
0$
#1095000
b11100011 4
0.
b1 3
b0 -
b1001110 0
1"
1$
#1100000
0"
0$
#1105000
b1 4
b10 3
b10001 -
b1001111 0
1"
1$
#1110000
0"
0$
#1115000
b0 4
b11 3
b0 -
b1010000 0
1"
1$
#1120000
0"
0$
b110101111100110100001101 %
b110101111100110100001101 (
#1125000
b100 3
b110101111100110100001101 2
b10111 -
b1010001 0
1"
1$
#1130000
0"
0$
#1135000
b101 3
b0 -
b1010010 0
1"
1$
#1140000
0"
0$
#1145000
b110 3
b10111 -
b1010011 0
1"
1$
#1150000
0"
0$
#1155000
b111 3
b0 -
b1010100 0
1"
1$
#1160000
0"
0$
#1165000
b11010111 4
1.
b0 3
b10111 -
b1010101 0
1"
1$
#1170000
0"
0$
#1175000
b11001101 4
0.
b1 3
b0 -
b1010110 0
1"
1$
#1180000
0"
0$
#1185000
b1101 4
b10 3
b10111 -
b1010111 0
1"
1$
#1190000
0"
0$
#1195000
b0 4
b11 3
b0 -
b1011000 0
1"
1$
#1200000
0"
0$
b1000111111000101110110 %
b1000111111000101110110 (
#1205000
b100 3
b1000111111000101110110 2
b10100100 -
b1011001 0
1"
1$
#1210000
0"
0$
#1215000
b101 3
b0 -
b1011010 0
1"
1$
#1220000
0"
0$
#1225000
b110 3
b10100100 -
b1011011 0
1"
1$
#1230000
0"
0$
#1235000
b111 3
b0 -
b1011100 0
1"
1$
#1240000
0"
0$
#1245000
b100011 4
1.
b0 3
b10100100 -
b1011101 0
1"
1$
#1250000
0"
0$
#1255000
b11110001 4
0.
b1 3
b0 -
b1011110 0
1"
1$
#1260000
0"
0$
#1265000
b1110110 4
b10 3
b10100100 -
b1011111 0
1"
1$
#1270000
0"
0$
#1275000
b0 4
b11 3
b0 -
b1100000 0
1"
1$
#1280000
0"
0$
b100011011100110100111101 %
b100011011100110100111101 (
#1285000
b100 3
b100011011100110100111101 2
b1111101 -
b1100001 0
1"
1$
#1290000
0"
0$
#1295000
b101 3
b0 -
b1100010 0
1"
1$
#1300000
0"
0$
#1305000
b110 3
b1111101 -
b1100011 0
1"
1$
#1310000
0"
0$
#1315000
b111 3
b0 -
b1100100 0
1"
1$
#1320000
0"
0$
#1325000
b10001101 4
1.
b0 3
b1111101 -
b1100101 0
1"
1$
#1330000
0"
0$
#1335000
b11001101 4
0.
b1 3
b0 -
b1100110 0
1"
1$
#1340000
0"
0$
#1345000
b111101 4
b10 3
b1111101 -
b1100111 0
1"
1$
#1350000
0"
0$
#1355000
b0 4
b11 3
b0 -
b1101000 0
1"
1$
#1360000
0"
0$
b110101000101011111101101 %
b110101000101011111101101 (
#1365000
b100 3
b110101000101011111101101 2
b1101110 -
b1101001 0
1"
1$
#1370000
0"
0$
#1375000
b101 3
b0 -
b1101010 0
1"
1$
#1380000
0"
0$
#1385000
b110 3
b1101110 -
b1101011 0
1"
1$
#1390000
0"
0$
#1395000
b111 3
b0 -
b1101100 0
1"
1$
#1400000
0"
0$
#1405000
b11010100 4
1.
b0 3
b1101110 -
b1101101 0
1"
1$
#1410000
0"
0$
#1415000
b1010111 4
0.
b1 3
b0 -
b1101110 0
0!
1"
1$
#1420000
0"
0$
#1425000
b11101101 4
b10 3
b1101110 -
b1101111 0
1"
1$
#1430000
0"
0$
#1435000
b0 4
b11 3
b0 -
b1110000 0
1"
1$
#1440000
0"
0$
b1011011111011110001100 %
b1011011111011110001100 (
#1445000
b100 3
b1011011111011110001100 2
b1010110 -
b1110001 0
1"
1$
#1450000
0"
0$
#1455000
b101 3
b0 -
b1110010 0
1"
1$
#1460000
0"
0$
#1465000
b110 3
b1010110 -
b1110011 0
1"
1$
#1470000
0"
0$
#1475000
b111 3
b0 -
b1110100 0
1"
1$
#1480000
0"
0$
#1485000
b101101 4
1.
b0 3
b1010110 -
b1110101 0
1"
1$
#1490000
0"
0$
#1495000
b11110111 4
0.
b1 3
b0 -
b1110110 0
1!
1"
1$
#1500000
0"
0$
#1505000
b10001100 4
b10 3
b1010110 -
b1110111 0
1"
1$
#1510000
0"
0$
#1515000
b0 4
b11 3
b0 -
b1111000 0
1"
1$
#1520000
0"
0$
b111111011110100111111001 %
b111111011110100111111001 (
#1525000
b100 3
b111111011110100111111001 2
b11101101 -
b1111001 0
1"
1$
#1530000
0"
0$
#1535000
b101 3
b0 -
b1111010 0
1"
1$
#1540000
0"
0$
#1545000
b110 3
b11101101 -
b1111011 0
1"
1$
#1550000
0"
0$
#1555000
b111 3
b0 -
b1111100 0
1"
1$
#1560000
0"
0$
#1565000
b11111101 4
1.
b0 3
b11101101 -
b1111101 0
1"
1$
#1570000
0"
0$
#1575000
b11101001 4
0.
b1 3
b0 -
b1111110 0
1"
1$
#1580000
0"
0$
#1585000
b11111001 4
b10 3
b11101101 -
b1111111 0
1"
1$
#1590000
0"
0$
#1595000
b0 4
b11 3
b0 -
b10000000 0
1"
1$
#1600000
0"
0$
b1101110010010011000110 %
b1101110010010011000110 (
#1605000
b100 3
b1101110010010011000110 2
b11010101 -
b10000001 0
1"
1$
#1610000
0"
0$
#1615000
b101 3
b0 -
b10000010 0
1"
1$
#1620000
0"
0$
#1625000
b110 3
b11010101 -
b10000011 0
1"
1$
#1630000
0"
0$
#1635000
b111 3
b0 -
b10000100 0
1"
1$
#1640000
0"
0$
#1645000
b110111 4
1.
b0 3
b11010101 -
b10000101 0
1"
1$
#1650000
0"
0$
#1655000
b100100 4
0.
b1 3
b0 -
b10000110 0
1"
1$
#1660000
0"
0$
#1665000
b11000110 4
b10 3
b11010101 -
b10000111 0
1"
1$
#1670000
0"
0$
#1675000
b0 4
b11 3
b0 -
b10001000 0
1"
1$
#1680000
0"
0$
b111101111000010011000101 %
b111101111000010011000101 (
#1685000
b100 3
b111101111000010011000101 2
b10110110 -
b10001001 0
1"
1$
#1690000
0"
0$
#1695000
b101 3
b0 -
b10001010 0
1"
1$
#1700000
0"
0$
#1705000
b110 3
b10110110 -
b10001011 0
1"
1$
#1710000
0"
0$
#1715000
b111 3
b0 -
b10001100 0
1"
1$
#1720000
0"
0$
#1725000
b11110111 4
1.
b0 3
b10110110 -
b10001101 0
1"
1$
#1730000
0"
0$
#1735000
b10000100 4
0.
b1 3
b0 -
b10001110 0
1"
1$
#1740000
0"
0$
#1745000
b11000101 4
b10 3
b10110110 -
b10001111 0
1"
1$
#1750000
0"
0$
#1755000
b0 4
b11 3
b0 -
b10010000 0
1"
1$
#1760000
0"
0$
b100111101001010101010 %
b100111101001010101010 (
#1765000
b100 3
b100111101001010101010 2
b1101011 -
b10010001 0
1"
1$
#1770000
0"
0$
#1775000
b101 3
b0 -
b10010010 0
1"
1$
#1780000
0"
0$
#1785000
b110 3
b1101011 -
b10010011 0
1"
1$
#1790000
0"
0$
#1795000
b111 3
b0 -
b10010100 0
1"
1$
#1800000
0"
0$
#1805000
b10011 4
1.
b0 3
b1101011 -
b10010101 0
1"
1$
#1810000
0"
0$
#1815000
b11010010 4
0.
b1 3
b0 -
b10010110 0
1"
1$
#1820000
0"
0$
#1825000
b10101010 4
b10 3
b1101011 -
b10010111 0
1"
1$
#1830000
0"
0$
#1835000
b0 4
b11 3
b0 -
b10011000 0
1"
1$
#1840000
0"
0$
b101011111111011111100101 %
b101011111111011111100101 (
#1845000
b100 3
b101011111111011111100101 2
b10111101 -
b10011001 0
1"
1$
#1850000
0"
0$
#1855000
b101 3
b0 -
b10011010 0
1"
1$
#1860000
0"
0$
#1865000
b110 3
b10111101 -
b10011011 0
1"
1$
#1870000
0"
0$
#1875000
b111 3
b0 -
b10011100 0
1"
1$
#1880000
0"
0$
#1885000
b10101111 4
1.
b0 3
b10111101 -
b10011101 0
1"
1$
#1890000
0"
0$
#1895000
b11110111 4
0.
b1 3
b0 -
b10011110 0
1"
1$
#1900000
0"
0$
#1905000
b11100101 4
b10 3
b10111101 -
b10011111 0
1"
1$
#1910000
0"
0$
#1915000
b0 4
b11 3
b0 -
b10100000 0
1"
1$
#1920000
0"
0$
b110100100111001001110111 %
b110100100111001001110111 (
#1925000
b100 3
b110100100111001001110111 2
b11010111 -
b10100001 0
1"
1$
#1930000
0"
0$
#1935000
b101 3
b0 -
b10100010 0
1"
1$
#1940000
0"
0$
#1945000
b110 3
b11010111 -
b10100011 0
1"
1$
#1950000
0"
0$
#1955000
b111 3
b0 -
b10100100 0
1"
1$
#1960000
0"
0$
#1965000
b11010010 4
1.
b0 3
b11010111 -
b10100101 0
1"
1$
#1970000
0"
0$
#1975000
b1110010 4
0.
b1 3
b0 -
b10100110 0
0!
1"
1$
#1980000
0"
0$
#1985000
b1110111 4
b10 3
b11010111 -
b10100111 0
1"
1$
#1990000
0"
0$
#1995000
b0 4
b11 3
b0 -
b10101000 0
1"
1$
#2000000
0"
0$
b1100101101011000010010 %
b1100101101011000010010 (
#2005000
b100 3
b1100101101011000010010 2
b11110110 -
b10101001 0
1"
1$
#2010000
0"
0$
#2015000
b101 3
b0 -
b10101010 0
1"
1$
#2020000
0"
0$
#2025000
b110 3
b11110110 -
b10101011 0
1"
1$
#2030000
0"
0$
#2035000
b111 3
b0 -
b10101100 0
1"
1$
#2040000
0"
0$
#2045000
b110010 4
1.
b0 3
b11110110 -
b10101101 0
1"
1$
#2050000
0"
0$
#2055000
b11010110 4
0.
b1 3
b0 -
b10101110 0
1"
1$
#2060000
0"
0$
#2065000
b10010 4
b10 3
b11110110 -
b10101111 0
1"
1$
#2070000
0"
0$
#2075000
b0 4
b11 3
b0 -
b10110000 0
1"
1$
#2080000
0"
0$
b111011001101101110001111 %
b111011001101101110001111 (
#2085000
b100 3
b111011001101101110001111 2
b10111000 -
b10110001 0
1"
1$
#2090000
0"
0$
#2095000
b101 3
b0 -
b10110010 0
1"
1$
#2100000
0"
0$
#2105000
b110 3
b10111000 -
b10110011 0
1"
1$
#2110000
0"
0$
#2115000
b111 3
b0 -
b10110100 0
1"
1$
#2120000
0"
0$
#2125000
b11101100 4
1.
b0 3
b10111000 -
b10110101 0
1"
1$
#2130000
0"
0$
#2135000
b11011011 4
0.
b1 3
b0 -
b10110110 0
1"
1$
#2140000
0"
0$
#2145000
b10001111 4
b10 3
b10111000 -
b10110111 0
1"
1$
#2150000
0"
0$
#2155000
b0 4
b11 3
b0 -
b10111000 0
1"
1$
#2160000
0"
0$
b1100000110100111110010 %
b1100000110100111110010 (
#2165000
b100 3
b1100000110100111110010 2
b10101011 -
b10111001 0
1"
1$
#2170000
0"
0$
#2175000
b101 3
b0 -
b10111010 0
1"
1$
#2180000
0"
0$
#2185000
b110 3
b10101011 -
b10111011 0
1"
1$
#2190000
0"
0$
#2195000
b111 3
b0 -
b10111100 0
1"
1$
#2200000
0"
0$
#2205000
b110000 4
1.
b0 3
b10101011 -
b10111101 0
1"
1$
#2210000
0"
0$
#2215000
b1101001 4
0.
b1 3
b0 -
b10111110 0
1"
1$
#2220000
0"
0$
#2225000
b11110010 4
b10 3
b10101011 -
b10111111 0
1"
1$
#2230000
0"
0$
#2235000
b0 4
b11 3
b0 -
b11000000 0
1"
1$
#2240000
0"
0$
b11101101001011011001110 %
b11101101001011011001110 (
#2245000
b100 3
b11101101001011011001110 2
b101110 -
b11000001 0
1"
1$
#2250000
0"
0$
#2255000
b101 3
b0 -
b11000010 0
1"
1$
#2260000
0"
0$
#2265000
b110 3
b101110 -
b11000011 0
1"
1$
#2270000
0"
0$
#2275000
b111 3
b0 -
b11000100 0
1"
1$
#2280000
0"
0$
#2285000
b1110110 4
1.
b0 3
b101110 -
b11000101 0
1"
1$
#2290000
0"
0$
#2295000
b10010110 4
0.
b1 3
b0 -
b11000110 0
1"
1$
#2300000
0"
0$
#2305000
b11001110 4
b10 3
b101110 -
b11000111 0
1"
1$
#2310000
0"
0$
#2315000
b0 4
b11 3
b0 -
b11001000 0
1"
1$
#2320000
0"
0$
b111101011101000 %
b111101011101000 (
#2325000
b100 3
b111101011101000 2
b10010010 -
b11001001 0
1"
1$
#2330000
0"
0$
#2335000
b101 3
b0 -
b11001010 0
1"
1$
#2340000
0"
0$
#2345000
b110 3
b10010010 -
b11001011 0
1"
1$
#2350000
0"
0$
#2355000
b111 3
b0 -
b11001100 0
1"
1$
#2360000
0"
0$
#2365000
1.
b0 3
b10010010 -
b11001101 0
1"
1$
#2370000
0"
0$
#2375000
b1111010 4
0.
b1 3
b0 -
b11001110 0
1"
1$
#2380000
0"
0$
#2385000
b11101000 4
b10 3
b10010010 -
b11001111 0
1"
1$
#2390000
0"
0$
#2395000
b0 4
b11 3
b0 -
b11010000 0
1"
1$
#2400000
0"
0$
b110010100100111011000101 %
b110010100100111011000101 (
#2405000
b100 3
b110010100100111011000101 2
b1000001 -
b11010001 0
1"
1$
#2410000
0"
0$
#2415000
b101 3
b0 -
b11010010 0
1"
1$
#2420000
0"
0$
#2425000
b110 3
b1000001 -
b11010011 0
1"
1$
#2430000
0"
0$
#2435000
b111 3
b0 -
b11010100 0
1"
1$
#2440000
0"
0$
#2445000
b11001010 4
1.
b0 3
b1000001 -
b11010101 0
1"
1$
#2450000
0"
0$
#2455000
b1001110 4
0.
b1 3
b0 -
b11010110 0
1"
1$
#2460000
0"
0$
#2465000
b11000101 4
b10 3
b1000001 -
b11010111 0
1"
1$
#2470000
0"
0$
#2475000
b0 4
b11 3
b0 -
b11011000 0
1"
1$
#2480000
0"
0$
b10110000100100101011100 %
b10110000100100101011100 (
#2485000
b100 3
b10110000100100101011100 2
b1001101 -
b11011001 0
1"
1$
#2490000
0"
0$
#2495000
b101 3
b0 -
b11011010 0
1"
1$
#2500000
0"
0$
#2505000
b110 3
b1001101 -
b11011011 0
1"
1$
#2510000
0"
0$
#2515000
b111 3
b0 -
b11011100 0
1"
1$
