rtl/apix_receiver.v
module apix_receiver (
    input wire        clk,         // Clock signal
    input wire        rst_n,       // Active-low reset
    input wire        apix_data,   // Serialized data from Transmitter
    input wire        apix_clk,    // Clock input from Transmitter
    output reg [23:0] pixel_data,  // Reconstructed pixel data (RGB)
    output reg        error_flag   // Error flag if CRC doesn't match
);

    // Internal signals
    reg [7:0]  serdes_data;         // Data for deserialization
    reg [2:0]  serdes_counter;      // 3-bit counter for deserializing 24-bit pixel data
    reg [7:0]  crc_calc;            // Calculated CRC for error checking
    reg [7:0]  crc_received;        // CRC received from transmitter
    reg [23:0] pixel_buffer;        // Buffer to store reconstructed pixel data
    reg [1:0]  state, next_state;   // State machine for receiver

    // State machine parameters
    localparam IDLE = 2'b00, SYNC = 2'b01, DATA = 2'b10, CRC = 2'b11;

    // Main sequential process
    always @(posedge clk or negedge rst_n) begin
        if (!rst_n) begin
            // Reset all signals
            state <= IDLE;
            serdes_counter <= 0;
            crc_calc <= 8'h00;
            error_flag <= 0;
        end else begin
            state <= next_state;

            // Deserialization logic
            if (state == DATA) begin
                pixel_buffer[serdes_counter*8 +: 8] <= apix_data; // Reconstruct pixel data from serialized bits
                crc_calc <= crc_calc ^ apix_data; // Update CRC calculation
                if (serdes_counter == 3'b111) begin
                    pixel_data <= pixel_buffer; // Output the 24-bit pixel data
                end
            end

            // CRC checking logic
            if (state == CRC) begin
                crc_received <= apix_data; // Receive CRC
                if (crc_received != crc_calc) begin
                    error_flag <= 1; // Set error flag if CRC doesn't match
                end else begin
                    error_flag <= 0; // No error
                end
            end
        end
    end

    // State machine logic
    always @(*) begin
        case (state)
            IDLE: next_state = (apix_data == 8'hFF) ? SYNC : IDLE; // Wait for sync pattern (0xFF)
            SYNC: next_state = DATA;
            DATA: next_state = (serdes_counter == 3'b111) ? CRC : DATA; // After receiving full pixel, check CRC
            CRC:  next_state = IDLE; // After CRC, go to IDLE
            default: next_state = IDLE;
        endcase
    end

    // Serialization Counter Update
    always @(posedge clk or negedge rst_n) begin
        if (!rst_n) begin
            serdes_counter <= 0;
        end else if (state == DATA) begin
            serdes_counter <= serdes_counter + 1;
        end else begin
            serdes_counter <= 0; // Reset counter after data received
        end
    end

endmodule

rtl/testbench/apix_receiver_tb.v
`timescale 1ns/1ps

module apix_receiver_tb;

    // Testbench signals
    reg clk;
    reg rst_n;
    reg apix_data;
    reg apix_clk;
    wire [23:0] pixel_data;
    wire error_flag;

        integer i; // Declare the loop variable

    // Clock generation parameters
    parameter CLK_PERIOD = 10; // 100MHz clock

    // Instantiate the DUT (Device Under Test)
    apix_receiver dut (
        .clk(clk),
        .rst_n(rst_n),
        .apix_data(apix_data),
        .apix_clk(apix_clk),
        .pixel_data(pixel_data),
        .error_flag(error_flag)
    );

    // Clock generation
    initial begin
        clk = 0;
        forever #(CLK_PERIOD/2) clk = ~clk;
    end

    // APIX Clock generation
    initial begin
        apix_clk = 0;
        forever #(CLK_PERIOD) apix_clk = ~apix_clk;
    end

    // Test stimulus
    initial begin

        // Initialize signals
        rst_n = 0;
        apix_data = 0;

        // Initialize dump file
        $dumpfile("apix_receiver_tb.vcd");
        $dumpvars(0, apix_receiver_tb);

        // Reset sequence
        #(CLK_PERIOD*5);
        rst_n = 1;
        #(CLK_PERIOD*5);

        // Test Case 1: Sending pixel data (24'hFFAA55)
        for (i = 23; i >= 0; i = i - 1) begin
            apix_data = (24'hFFAA55 >> i) & 1'b1;
            #(CLK_PERIOD);
        end
        #(CLK_PERIOD*20);

        // Test Case 2: Sending pixel data with incorrect CRC (24'h123456, CRC 8'hFF)
        for (i = 23; i >= 0; i = i - 1) begin
            apix_data = (24'h123456 >> i) & 1'b1;
            #(CLK_PERIOD);
        end
        for (i = 7; i >= 0; i = i - 1) begin
            apix_data = (8'hFF >> i) & 1'b1;
            #(CLK_PERIOD);
        end
        #(CLK_PERIOD*20);

        // Test Case 3: Sending pixel data with correct CRC (24'h789ABC, correct CRC)
        for (i = 23; i >= 0; i = i - 1) begin
            apix_data = (24'h789ABC >> i) & 1'b1;
            #(CLK_PERIOD);
        end
        for (i = 7; i >= 0; i = i - 1) begin
            apix_data = (dut.crc_calc >> i) & 1'b1;
            #(CLK_PERIOD);
        end
        #(CLK_PERIOD*20);

        // End simulation
        $display("Simulation completed successfully");
        $finish;
    end

endmodule

rtl/sim_files/apix_receiver_tb.vcd
$date
	Tue Nov 12 15:03:20 2024
$end
$version
	Icarus Verilog
$end
$timescale
	1ps
$end
$scope module apix_receiver_tb $end
$var wire 24 ! pixel_data [23:0] $end
$var wire 1 " error_flag $end
$var parameter 32 # CLK_PERIOD $end
$var reg 1 $ apix_clk $end
$var reg 1 % apix_data $end
$var reg 1 & clk $end
$var reg 1 ' rst_n $end
$var integer 32 ( i [31:0] $end
$scope module dut $end
$var wire 1 $ apix_clk $end
$var wire 1 % apix_data $end
$var wire 1 & clk $end
$var wire 1 ' rst_n $end
$var parameter 2 ) CRC $end
$var parameter 2 * DATA $end
$var parameter 2 + IDLE $end
$var parameter 2 , SYNC $end
$var reg 8 - crc_calc [7:0] $end
$var reg 8 . crc_received [7:0] $end
$var reg 1 " error_flag $end
$var reg 2 / next_state [1:0] $end
$var reg 24 0 pixel_buffer [23:0] $end
$var reg 24 1 pixel_data [23:0] $end
$var reg 3 2 serdes_counter [2:0] $end
$var reg 2 3 state [1:0] $end
$upscope $end
$upscope $end
$enddefinitions $end
$comment Show the parameter values. $end
$dumpall
b1 ,
b0 +
b10 *
b11 )
b1010 #
$end
#0
$dumpvars
b0 3
b0 2
bx 1
bx 0
b0 /
bx .
b0 -
bx (
0'
0&
0%
0$
0"
bx !
$end
#5000
1&
#10000
0&
1$
#15000
1&
#20000
0&
0$
#25000
1&
#30000
0&
1$
#35000
1&
#40000
0&
0$
#45000
1&
#50000
0&
1$
1'
#55000
1&
#60000
0&
0$
#65000
1&
#70000
0&
1$
#75000
1&
#80000
0&
0$
#85000
1&
#90000
0&
1$
#95000
1&
#100000
0&
0$
1%
b10111 (
#105000
1&
#110000
0&
1$
b10110 (
#115000
1&
#120000
0&
0$
b10101 (
#125000
1&
#130000
0&
1$
b10100 (
#135000
1&
#140000
0&
0$
b10011 (
#145000
1&
#150000
0&
1$
b10010 (
#155000
1&
#160000
0&
0$
b10001 (
#165000
1&
#170000
0&
1$
b10000 (
#175000
1&
#180000
0&
0$
b1111 (
#185000
1&
#190000
0&
1$
0%
b1110 (
#195000
1&
#200000
0&
0$
1%
b1101 (
#205000
1&
#210000
0&
1$
0%
b1100 (
#215000
1&
#220000
0&
0$
1%
b1011 (
#225000
1&
#230000
0&
1$
0%
b1010 (
#235000
1&
#240000
0&
0$
1%
b1001 (
#245000
1&
#250000
0&
1$
0%
b1000 (
#255000
1&
#260000
0&
0$
b111 (
#265000
1&
#270000
0&
1$
1%
b110 (
#275000
1&
#280000
0&
0$
0%
b101 (
#285000
1&
#290000
0&
1$
1%
b100 (
#295000
1&
#300000
0&
0$
0%
b11 (
#305000
1&
#310000
0&
1$
1%
b10 (
#315000
1&
#320000
0&
0$
0%
b1 (
#325000
1&
#330000
0&
1$
1%
b0 (
#335000
1&
#340000
0&
0$
b11111111111111111111111111111111 (
#345000
1&
#350000
0&
1$
#355000
1&
#360000
0&
0$
#365000
1&
#370000
0&
1$
#375000
1&
#380000
0&
0$
#385000
1&
#390000
0&
1$
#395000
1&
#400000
0&
0$
#405000
1&
#410000
0&
1$
#415000
1&
#420000
0&
0$
#425000
1&
#430000
0&
1$
#435000
1&
#440000
0&
0$
#445000
1&
#450000
0&
1$
#455000
1&
#460000
0&
0$
#465000
1&
#470000
0&
1$
#475000
1&
#480000
0&
0$
#485000
1&
#490000
0&
1$
#495000
1&
#500000
0&
0$
#505000
1&
#510000
0&
1$
#515000
1&
#520000
0&
0$
#525000
1&
#530000
0&
1$
#535000
1&
#540000
0&
0$
0%
b10111 (
#545000
1&
#550000
0&
1$
b10110 (
#555000
1&
#560000
0&
0$
b10101 (
#565000
1&
#570000
0&
1$
1%
b10100 (
#575000
1&
#580000
0&
0$
0%
b10011 (
#585000
1&
#590000
0&
1$
b10010 (
#595000
1&
#600000
0&
0$
1%
b10001 (
#605000
1&
#610000
0&
1$
0%
b10000 (
#615000
1&
#620000
0&
0$
b1111 (
#625000
1&
#630000
0&
1$
b1110 (
#635000
1&
#640000
0&
0$
1%
b1101 (
#645000
1&
#650000
0&
1$
b1100 (
#655000
1&
#660000
0&
0$
0%
b1011 (
#665000
1&
#670000
0&
1$
1%
b1010 (
#675000
1&
#680000
0&
0$
0%
b1001 (
#685000
1&
#690000
0&
1$
b1000 (
#695000
1&
#700000
0&
0$
b111 (
#705000
1&
#710000
0&
1$
1%
b110 (
#715000
1&
#720000
0&
0$
0%
b101 (
#725000
1&
#730000
0&
1$
1%
b100 (
#735000
1&
#740000
0&
0$
0%
b11 (
#745000
1&
#750000
0&
1$
1%
b10 (
#755000
1&
#760000
0&
0$
b1 (
#765000
1&
#770000
0&
1$
0%
b0 (
#775000
1&
#780000
0&
0$
1%
b111 (
#785000
1&
#790000
0&
1$
b110 (
#795000
1&
#800000
0&
0$
b101 (
#805000
1&
#810000
0&
1$
b100 (
#815000
1&
#820000
0&
0$
b11 (
#825000
1&
#830000
0&
1$
b10 (
#835000
1&
#840000
0&
0$
b1 (
#845000
1&
#850000
0&
1$
b0 (
#855000
1&
#860000
0&
0$
b11111111111111111111111111111111 (
#865000
1&
#870000
0&
1$
#875000
1&
#880000
0&
0$
#885000
1&
#890000
0&
1$
#895000
1&
#900000
0&
0$
#905000
1&
#910000
0&
1$
#915000
1&
#920000
0&
0$
#925000
1&
#930000
0&
1$
#935000
1&
#940000
0&
0$
#945000
1&
#950000
0&
1$
#955000
1&
#960000
0&
0$
#965000
1&
#970000
0&
1$
#975000
1&
#980000
0&
0$
#985000
1&
#990000
0&
1$
#995000
1&
#1000000
0&
0$
#1005000
1&
#1010000
0&
1$
#1015000
1&
#1020000
0&
0$
#1025000
1&
#1030000
0&
1$
#1035000
1&
#1040000
0&
0$
#1045000
1&
#1050000
0&
1$
#1055000
1&
#1060000
0&
0$
0%
b10111 (
#1065000
1&
#1070000
0&
1$
1%
b10110 (
#1075000
1&
#1080000
0&
0$
b10101 (
#1085000
1&
#1090000
0&
1$
b10100 (
#1095000
1&
#1100000
0&
0$
b10011 (
#1105000
1&
#1110000
0&
1$
0%
b10010 (
#1115000
1&
#1120000
0&
0$
b10001 (
#1125000
1&
#1130000
0&
1$
b10000 (
#1135000
1&
#1140000
0&
0$
1%
b1111 (
#1145000
1&
#1150000
0&
1$
0%
b1110 (
#1155000
1&
#1160000
0&
0$
b1101 (
#1165000
1&
#1170000
0&
1$
1%
b1100 (
#1175000
1&
#1180000
0&
0$
b1011 (
#1185000
1&
#1190000
0&
1$
0%
b1010 (
#1195000
1&
#1200000
0&
0$
1%
b1001 (
#1205000
1&
#1210000
0&
1$
0%
b1000 (
#1215000
1&
#1220000
0&
0$
1%
b111 (
#1225000
1&
#1230000
0&
1$
0%
b110 (
#1235000
1&
#1240000
0&
0$
1%
b101 (
#1245000
1&
#1250000
0&
1$
b100 (
#1255000
1&
#1260000
0&
0$
b11 (
#1265000
1&
#1270000
0&
1$
b10 (
#1275000
1&
#1280000
0&
0$
0%
b1 (
#1285000
1&
#1290000
0&
1$
b0 (
#1295000
1&
#1300000
0&
0$
b111 (
#1305000
1&
#1310000
0&
1$
b110 (
#1315000
1&
#1320000
0&
0$
b101 (
#1325000
1&
#1330000
0&
1$
b100 (
#1335000
1&
#1340000
0&
0$
b11 (
#1345000
1&
#1350000
0&
1$
b10 (
#1355000
1&
#1360000
0&
0$
b1 (
#1365000
1&
#1370000
0&
1$
b0 (
#1375000
1&
#1380000
0&
0$
b11111111111111111111111111111111 (
